pyad/__init__.py
pyad/forward_mode.py
pyad/graph_demo.py
pyad/nn.py
pyad/random_testing.py
pyad/reverse_mode.py
pyad/tests/__init__.py
pyad/tests/test_forward_mode.py
pyad/tests/test_forward_mode_end2end.py
pyad/tests/test_nn.py
pyad/tests/test_reverse.py
pyad207-1.0.1.dist-info/LICENSE
pyad207-1.0.1.dist-info/METADATA
pyad207-1.0.1.dist-info/WHEEL
pyad207-1.0.1.dist-info/top_level.txt
pyad207-1.0.1.dist-info/RECORD
